paises/__init__.py
paises/alias.py
paises/cache/backup/acp.json
paises/cache/backup/ag.json
paises/cache/backup/aosis.json
paises/cache/backup/ap.json
paises/cache/backup/asean.json
paises/cache/backup/au.json
paises/cache/backup/canz.json
paises/cache/backup/caricom.json
paises/cache/backup/cegpl.json
paises/cache/backup/cplp.json
paises/cache/backup/cw.json
paises/cache/backup/ecowas.json
paises/cache/backup/eeg.json
paises/cache/backup/eu.json
paises/cache/backup/g20.json
paises/cache/backup/g24.json
paises/cache/backup/g77.json
paises/cache/backup/gcc.json
paises/cache/backup/hics.json
paises/cache/backup/ida.json
paises/cache/backup/las.json
paises/cache/backup/ldcs.json
paises/cache/backup/lics.json
paises/cache/backup/lldcs.json
paises/cache/backup/lmcs.json
paises/cache/backup/nam.json
paises/cache/backup/nordic.json
paises/cache/backup/oecd.json
paises/cache/backup/oic.json
paises/cache/backup/pif.json
paises/cache/backup/sadc.json
paises/cache/backup/sica.json
paises/cache/backup/sids.json
paises/cache/backup/umcs.json
paises/cache/backup/un.json
paises/cache/backup/weog.json
paises/cache/backup/zangger.json
paises/cache/countries.json
paises/cache.py
paises/ccs.py
paises/countries.json
paises/countries.py
paises/country.py
paises/data.py
paises/groups/acd.json
paises/groups/acp.json
paises/groups/ag.json
paises/groups/aosis.json
paises/groups/ap.json
paises/groups/asean.json
paises/groups/au.json
paises/groups/brics.json
paises/groups/can.json
paises/groups/canz.json
paises/groups/caricom.json
paises/groups/cegpl.json
paises/groups/cplp.json
paises/groups/cw.json
paises/groups/eac.json
paises/groups/ecowas.json
paises/groups/eu.json
paises/groups/g20.json
paises/groups/g24.json
paises/groups/g77.json
paises/groups/gcc.json
paises/groups/grulac.json
paises/groups/hics.json
paises/groups/ida.json
paises/groups/ioc.json
paises/groups/las.json
paises/groups/ldcs.json
paises/groups/lics.json
paises/groups/lldcs.json
paises/groups/lmcs.json
paises-0.2.5.dist-info/WHEEL
paises-0.2.5.dist-info/METADATA
paises-0.2.5.dist-info/RECORD
