Metadata-Version: 2.1
Name: paises
Version: 0.2.5
Summary: 
Author: Tomas
Author-email: tomasgonz@gmail.com
Requires-Python: >=3.10,<4.0
Classifier: Programming Language :: Python :: 3
Classifier: Programming Language :: Python :: 3.10
Classifier: Programming Language :: Python :: 3.11
Requires-Dist: importlib (>=1.0.4,<2.0.0)
Requires-Dist: pytest (>=7.1.3,<8.0.0)
Requires-Dist: texttable (>=1.6.4,<2.0.0)
